aio_broadcast/__init__.py
aio_broadcast/broadcast.py
aio_broadcast-1.0.3.dist-info/METADATA
aio_broadcast-1.0.3.dist-info/WHEEL
aio_broadcast-1.0.3.dist-info/licenses/LICENSE
aio_broadcast-1.0.3.dist-info/RECORD
