Metadata-Version: 2.4
Name: aio-broadcast
Version: 1.0.3
Summary: Multi consumers asyncio compatible queue
Project-URL: Homepage, https://github.com/pytek-io/aio-broadcast
Project-URL: Issues, https://github.com/pypa/sampleproject/issues
Author-email: fdv1 <francois@pytek.io>
License:                     GNU GENERAL PUBLIC LICENSE
License-File: LICENSE
Keywords: asyncio,multi-consumers,queue
Requires-Python: >=3.8
Provides-Extra: dev
Requires-Dist: flake8-pyproject; extra == 'dev'
Requires-Dist: pytest; extra == 'dev'
Requires-Dist: pytest-asyncio; extra == 'dev'
Requires-Dist: pytest-cov; extra == 'dev'
